pandas_profiling/__init__.py
pandas_profiling/config.py
pandas_profiling/config_default.yaml
pandas_profiling/config_minimal.yaml
pandas_profiling/profile_report.py
pandas_profiling/serialize_report.py
pandas_profiling/version.py
pandas_profiling/controller/__init__.py
pandas_profiling/controller/console.py
pandas_profiling/controller/pandas_decorator.py
pandas_profiling/model/__init__.py
pandas_profiling/model/base.py
pandas_profiling/model/correlations.py
pandas_profiling/model/describe.py
pandas_profiling/model/messages.py
pandas_profiling/model/sample.py
pandas_profiling/model/summary.py
pandas_profiling/report/__init__.py
pandas_profiling/report/formatters.py
pandas_profiling/report/presentation/__init__.py
pandas_profiling/report/presentation/frequency_table_utils.py
pandas_profiling/report/presentation/core/__init__.py
pandas_profiling/report/presentation/core/collapse.py
pandas_profiling/report/presentation/core/container.py
pandas_profiling/report/presentation/core/duplicate.py
pandas_profiling/report/presentation/core/frequency_table.py
pandas_profiling/report/presentation/core/frequency_table_small.py
pandas_profiling/report/presentation/core/html.py
pandas_profiling/report/presentation/core/image.py
pandas_profiling/report/presentation/core/item_renderer.py
pandas_profiling/report/presentation/core/renderable.py
pandas_profiling/report/presentation/core/root.py
pandas_profiling/report/presentation/core/sample.py
pandas_profiling/report/presentation/core/table.py
pandas_profiling/report/presentation/core/toggle_button.py
pandas_profiling/report/presentation/core/variable.py
pandas_profiling/report/presentation/core/variable_info.py
pandas_profiling/report/presentation/core/warnings.py
pandas_profiling/report/presentation/flavours/__init__.py
pandas_profiling/report/presentation/flavours/flavours.py
pandas_profiling/report/presentation/flavours/html/__init__.py
pandas_profiling/report/presentation/flavours/html/collapse.py
haiqv_profiling-0.0.1.dist-info/LICENSE
haiqv_profiling-0.0.1.dist-info/METADATA
haiqv_profiling-0.0.1.dist-info/WHEEL
haiqv_profiling-0.0.1.dist-info/entry_points.txt
haiqv_profiling-0.0.1.dist-info/top_level.txt
haiqv_profiling-0.0.1.dist-info/RECORD
