Metadata-Version: 2.1
Name: haiqv-profiling
Version: 0.0.1
Summary: Generate profile report for pandas DataFrame
Home-page: https://github.com/pandas-profiling/pandas-profiling
Author: dataman
Author-email: itb001@hanwha.com
License: MIT
Keywords: pandas data-science data-analysis python jupyter ipython
Platform: UNKNOWN
Classifier: Development Status :: 5 - Production/Stable
Classifier: Topic :: Software Development :: Build Tools
Classifier: License :: OSI Approved :: MIT License
Classifier: Environment :: Console
Classifier: Operating System :: OS Independent
Classifier: Intended Audience :: Science/Research
Classifier: Intended Audience :: Developers
Classifier: Intended Audience :: Financial and Insurance Industry
Classifier: Intended Audience :: Healthcare Industry
Classifier: Topic :: Scientific/Engineering
Classifier: Framework :: IPython
Classifier: Programming Language :: Python :: 3
Classifier: Programming Language :: Python :: 3.6
Classifier: Programming Language :: Python :: 3.7
Classifier: Programming Language :: Python :: 3.8
Classifier: Programming Language :: Python :: 3.9
Requires-Python: >=3.6
Requires-Dist: joblib
Requires-Dist: scipy (>=1.4.1)
Requires-Dist: pandas (!=1.0.0,!=1.0.1,!=1.0.2,!=1.1.0,>=0.25.3)
Requires-Dist: matplotlib (>=3.2.0)
Requires-Dist: confuse (>=1.0.0)
Requires-Dist: jinja2 (>=2.11.1)
Requires-Dist: visions[type_image_path] (==0.6.0)
Requires-Dist: numpy (>=1.16.0)
Requires-Dist: attrs (>=19.3.0)
Requires-Dist: htmlmin (>=0.1.12)
Requires-Dist: missingno (>=0.4.2)
Requires-Dist: phik (>=0.9.10)
Requires-Dist: tangled-up-in-unicode (>=0.0.6)
Requires-Dist: requests (>=2.23.0)
Requires-Dist: tqdm (>=4.43.0)
Requires-Dist: ipywidgets (>=7.5.1)
Requires-Dist: seaborn (>=0.10.1)
Provides-Extra: notebook
Requires-Dist: jupyter-client (>=6.0.0) ; extra == 'notebook'
Requires-Dist: jupyter-core (>=4.6.3) ; extra == 'notebook'
